qgs/__init__.py
qgs/basis/__init__.py
qgs/basis/base.py
qgs/basis/fourier.py
qgs/diagnostics/__init__.py
qgs/diagnostics/base.py
qgs/diagnostics/differential.py
qgs/diagnostics/eddy.py
qgs/diagnostics/misc.py
qgs/diagnostics/multi.py
qgs/diagnostics/streamfunctions.py
qgs/diagnostics/temperatures.py
qgs/diagnostics/util.py
qgs/diagnostics/variables.py
qgs/diagnostics/vorticity.py
qgs/diagnostics/wind.py
qgs/functions/__init__.py
qgs/functions/sparse_mul.py
qgs/functions/symbolic_mul.py
qgs/functions/symbolic_tendencies.py
qgs/functions/tendencies.py
qgs/functions/util.py
qgs/inner_products/__init__.py
qgs/inner_products/analytic.py
qgs/inner_products/base.py
qgs/inner_products/definition.py
qgs/inner_products/symbolic.py
qgs/integrators/__init__.py
qgs/integrators/integrate.py
qgs/integrators/integrator.py
qgs/integrators/statistics.py
qgs/params/__init__.py
qgs/params/parameter.py
qgs/params/params.py
qgs/plotting/__init__.py
qgs/plotting/util.py
qgs/tensors/__init__.py
qgs/tensors/atmo_thermo_tensor.py
qgs/tensors/qgtensor.py
qgs/tensors/symbolic_qgtensor.py
qgs/toolbox/__init__.py
qgs/toolbox/lyapunov.py
qgs-1.0.0.dist-info/licenses/LICENSE.txt
qgs-1.0.0.dist-info/METADATA
qgs-1.0.0.dist-info/WHEEL
qgs-1.0.0.dist-info/top_level.txt
qgs-1.0.0.dist-info/RECORD
