Metadata-Version: 2.4
Name: qgs
Version: 1.0.0
Summary: A 2-layer quasi-geostrophic atmospheric model. Can be coupled to a simple land or shallow-water ocean component.
Author-email: qgs Developers and Contributors <jodemaey@meteo.be>
License: 
Project-URL: homepage, https://github.com/Climdyn/qgs
Project-URL: documentation, https://qgs.readthedocs.io
Keywords: meteorology,climate,climate-variability,atmospheric-models,ocean-atmosphere-model
Classifier: License :: OSI Approved :: MIT License
Classifier: Programming Language :: Python
Classifier: Programming Language :: Python :: 3
Classifier: Programming Language :: Python :: 3.9
Classifier: Programming Language :: Python :: 3.10
Classifier: Programming Language :: Python :: 3.11
Classifier: Operating System :: OS Independent
Classifier: Development Status :: 5 - Production/Stable
Classifier: Framework :: Jupyter
Classifier: Intended Audience :: Science/Research
Classifier: Topic :: Scientific/Engineering :: Atmospheric Science
Requires-Python: >=3.9
License-File: LICENSE.txt
Requires-Dist: ipython
Requires-Dist: jupyter
Requires-Dist: matplotlib>=3.4
Requires-Dist: numba
Requires-Dist: numpy
Requires-Dist: scipy
Requires-Dist: sympy
Requires-Dist: sparse
Requires-Dist: pebble
Dynamic: license-file
